xqcsendmessage/__init__.py
xqcsendmessage/api.py
xqcsendmessage/client.py
xqcsendmessage/core/__init__.py
xqcsendmessage/core/abc.py
xqcsendmessage/core/exceptions.py
xqcsendmessage/core/logger.py
xqcsendmessage/core/utils.py
xqcsendmessage/dingtalk/__init__.py
xqcsendmessage/dingtalk/sender.py
xqcsendmessage/email/__init__.py
xqcsendmessage/email/sender.py
xqcsendmessage/wecom/__init__.py
xqcsendmessage/wecom/sender.py
xqcsendmessage-0.1.1.dist-info/LICENSE
xqcsendmessage-0.1.1.dist-info/METADATA
xqcsendmessage-0.1.1.dist-info/WHEEL
xqcsendmessage-0.1.1.dist-info/RECORD
