Metadata-Version: 2.3
Name: xqcsendmessage
Version: 0.1.1
Summary: 一个 XiaoqiangClub 自用的消息发送模块
License: MIT
Keywords: message,sender,dingtalk,wecom,email,webhook
Author: Xiaoqiang
Author-email: xiaoqiangclub@hotmail.com
Requires-Python: >=3.10
Classifier: Development Status :: 4 - Beta
Classifier: Intended Audience :: Developers
Classifier: License :: OSI Approved :: MIT License
Classifier: Operating System :: OS Independent
Classifier: Programming Language :: Python :: 3
Classifier: Programming Language :: Python :: 3.10
Classifier: Programming Language :: Python :: 3.11
Classifier: Programming Language :: Python :: 3.12
Classifier: Programming Language :: Python :: 3.13
Classifier: Topic :: Communications
Classifier: Topic :: Software Development :: Libraries :: Python Modules
Requires-Dist: aiofiles (>=23.2.1,<24.0.0)
Requires-Dist: aiosmtplib (>=5.0.0,<6.0.0)
Requires-Dist: httpx (>=0.20.0)
Project-URL: Documentation, https://github.com/xiaoqiangclub/XQCSendMessage
Project-URL: Homepage, https://github.com/xiaoqiangclub/XQCSendMessage
Project-URL: Repository, https://github.com/xiaoqiangclub/XQCSendMessage
